Code2cloudNB/__init__.py
Code2cloudNB/handler.py
code2cloudnb-0.1.3.dist-info/licenses/LICENSE
code2cloudnb-0.1.3.dist-info/METADATA
code2cloudnb-0.1.3.dist-info/WHEEL
code2cloudnb-0.1.3.dist-info/top_level.txt
code2cloudnb-0.1.3.dist-info/RECORD
