Metadata-Version: 2.4
Name: Code2cloudNB
Version: 0.1.3
Summary: A Python package providing helper functions to programmatically import Jupyter notebook content into Cloud platforms via REST APIs.
Home-page: https://github.com/antick-coder/Code2cloudNB.git
Author: Antick Mazumder
Author-email: antick.majumder@gmail.com
Classifier: Programming Language :: Python :: 3
Classifier: License :: OSI Approved :: MIT License
Classifier: Operating System :: OS Independent
Requires-Python: >=3.9
License-File: LICENSE
Dynamic: author
Dynamic: author-email
Dynamic: classifier
Dynamic: description
Dynamic: description-content-type
Dynamic: home-page
Dynamic: license-file
Dynamic: requires-python
Dynamic: summary
